{
  "color": {
    "$type": "color",
    "base": {
      "white": { "$value": "#ffffff" },
      "black": { "$value": "#000000" },
      "transparent": { "$value": "rgba(255, 255, 255, 0)" }
    },
    "gray": {
      "25": { "$value": "#fdfdfd" },
      "50": { "$value": "#fafafa" },
      "100": { "$value": "#f5f5f5" },
      "200": { "$value": "#e9eaeb" },
      "300": { "$value": "#d5d7da" },
      "400": { "$value": "#a4a7ae" },
      "500": { "$value": "#717680" },
      "600": { "$value": "#535862" },
      "700": { "$value": "#414651" },
      "800": { "$value": "#252b37" },
      "900": { "$value": "#181d27" },
      "950": { "$value": "#0a0d12" }
    },
    "brand": {
      "25": { "$value": "#fcfaff" },
      "50": { "$value": "#f9f5ff" },
      "100": { "$value": "#f4ebff" },
      "200": { "$value": "#e9d7fe" },
      "300": { "$value": "#d6bbfb" },
      "400": { "$value": "#b692f6" },
      "500": { "$value": "#9e77ed" },
      "600": { "$value": "#7f56d9" },
      "700": { "$value": "#6941c6" },
      "800": { "$value": "#53389e" },
      "900": { "$value": "#42307d" },
      "950": { "$value": "#2c1c5f" }
    },
    "error": {
      "25": { "$value": "#fffbfa" },
      "50": { "$value": "#fef3f2" },
      "100": { "$value": "#fee4e2" },
      "200": { "$value": "#fecdca" },
      "300": { "$value": "#fda29b" },
      "400": { "$value": "#f97066" },
      "500": { "$value": "#f04438" },
      "600": { "$value": "#d92d20" },
      "700": { "$value": "#b42318" },
      "800": { "$value": "#912018" },
      "900": { "$value": "#7a271a" },
      "950": { "$value": "#55160c" }
    },
    "warning": {
      "25": { "$value": "#fffcf5" },
      "50": { "$value": "#fffaeb" },
      "100": { "$value": "#fef0c7" },
      "200": { "$value": "#fedf89" },
      "300": { "$value": "#fec84b" },
      "400": { "$value": "#fdb022" },
      "500": { "$value": "#f79009" },
      "600": { "$value": "#dc6803" },
      "700": { "$value": "#b54708" },
      "800": { "$value": "#93370d" },
      "900": { "$value": "#7a2e0e" },
      "950": { "$value": "#4e1d09" }
    },
    "success": {
      "25": { "$value": "#f6fef9" },
      "50": { "$value": "#ecfdf3" },
      "100": { "$value": "#dcfae6" },
      "200": { "$value": "#abefc6" },
      "300": { "$value": "#75e0a7" },
      "400": { "$value": "#47cd89" },
      "500": { "$value": "#17b26a" },
      "600": { "$value": "#079455" },
      "700": { "$value": "#067647" },
      "800": { "$value": "#085d3a" },
      "900": { "$value": "#074d31" },
      "950": { "$value": "#053321" }
    },
    "blue-light": {
      "25": { "$value": "#f5fbff" },
      "50": { "$value": "#f0f9ff" },
      "100": { "$value": "#e0f2fe" },
      "200": { "$value": "#b9e6fe" },
      "300": { "$value": "#7cd4fd" },
      "400": { "$value": "#36bffa" },
      "500": { "$value": "#0ba5ec" },
      "600": { "$value": "#0086c9" },
      "700": { "$value": "#026aa2" },
      "800": { "$value": "#065986" },
      "900": { "$value": "#0b4a6f" },
      "950": { "$value": "#062c41" }
    },
    "blue": {
      "25": { "$value": "#f5faff" },
      "50": { "$value": "#eff8ff" },
      "100": { "$value": "#d1e9ff" },
      "200": { "$value": "#b2ddff" },
      "300": { "$value": "#84caff" },
      "400": { "$value": "#53b1fd" },
      "500": { "$value": "#2e90fa" },
      "600": { "$value": "#1570ef" },
      "700": { "$value": "#175cd3" },
      "800": { "$value": "#1849a9" },
      "900": { "$value": "#194185" },
      "950": { "$value": "#102a56" }
    },
    "indigo": {
      "25": { "$value": "#f5f8ff" },
      "50": { "$value": "#eef4ff" },
      "100": { "$value": "#e0eaff" },
      "200": { "$value": "#c7d7fe" },
      "300": { "$value": "#a4bcfd" },
      "400": { "$value": "#8098f9" },
      "500": { "$value": "#6172f3" },
      "600": { "$value": "#444ce7" },
      "700": { "$value": "#3538cd" },
      "800": { "$value": "#2d31a6" },
      "900": { "$value": "#2d3282" },
      "950": { "$value": "#1f235b" }
    },
    "purple": {
      "25": { "$value": "#fafaff" },
      "50": { "$value": "#f4f3ff" },
      "100": { "$value": "#ebe9fe" },
      "200": { "$value": "#d9d6fe" },
      "300": { "$value": "#bdb4fe" },
      "400": { "$value": "#9b8afb" },
      "500": { "$value": "#7a5af8" },
      "600": { "$value": "#6938ef" },
      "700": { "$value": "#5925dc" },
      "800": { "$value": "#4a1fb8" },
      "900": { "$value": "#3e1c96" },
      "950": { "$value": "#27115f" }
    },
    "pink": {
      "25": { "$value": "#fef6fb" },
      "50": { "$value": "#fdf2fa" },
      "100": { "$value": "#fce7f6" },
      "200": { "$value": "#fcceee" },
      "300": { "$value": "#faa7e0" },
      "400": { "$value": "#f670c7" },
      "500": { "$value": "#ee46bc" },
      "600": { "$value": "#dd2590" },
      "700": { "$value": "#c11574" },
      "800": { "$value": "#9e165f" },
      "900": { "$value": "#851651" },
      "950": { "$value": "#4e0d30" }
    },
    "orange": {
      "25": { "$value": "#fefaf5" },
      "50": { "$value": "#fef6ee" },
      "100": { "$value": "#fdead7" },
      "200": { "$value": "#f9dbaf" },
      "300": { "$value": "#f7b27a" },
      "400": { "$value": "#f38744" },
      "500": { "$value": "#ef6820" },
      "600": { "$value": "#e04f16" },
      "700": { "$value": "#b93815" },
      "800": { "$value": "#932f19" },
      "900": { "$value": "#772917" },
      "950": { "$value": "#511c10" }
    }
  }
}
